{"@verdaccio/auth":{"6":617,"7":10610,"8":647830,"9":431},"@verdaccio/config":{"6":242490,"7":18989,"8":648605,"9":2976},"@verdaccio/core":{"6":242398,"7":19274,"8":975336,"9":3454},"@verdaccio/hooks":{"6":597,"7":35,"8":317572,"9":516},"@verdaccio/loaders":{"6":611,"7":10516,"8":647939,"9":729},"@verdaccio/node-api":{"6":169,"7":13,"8":25,"9":245},"@verdaccio/server":{"6":168,"7":13,"8":23,"9":218},"@verdaccio/active-directory":{"8":13,"9":16,"10":42,"11":8},"@verdaccio/local-storage":{"0":81,"1":1489,"2":385,"8":490,"9":6563,"10":63210,"11":583,"12":18,"13":83,"14":313},"@verdaccio/package-filter":{"13":162729,"14":307},"verdaccio-google-cloud":{"0":8,"8":4,"9":18,"10":271,"11":205},"verdaccio-aws-s3-storage":{"0":5,"8":25,"9":28,"10":1334,"11":14,"12":2452},"@verdaccio/local-storage-legacy":{"11":639186},"@verdaccio/logger":{"6":602,"7":10508,"8":646814,"9":958},"@verdaccio/middleware":{"6":7748,"7":18937,"8":647617,"9":474},"@verdaccio/proxy":{"6":656,"7":51,"8":31,"9":358},"@verdaccio/search-indexer":{"7":12331,"8":637638,"9":128},"@verdaccio/signature":{"6":5106,"7":18644,"8":647714,"9":454},"@verdaccio/streams":{"0":235,"1":1484,"2":463,"8":1427,"9":7073,"10":698613,"11":2425},"@verdaccio/tarball":{"11":12560,"12":18840,"13":639357,"14":426},"@verdaccio/ui-theme":{"0":1098,"1":6399,"2":4,"3":36005,"4":2,"6":22536,"7":18690,"8":486920,"9":150016},"@verdaccio/url":{"11":12677,"12":18806,"13":647716,"14":478},"@verdaccio/e2e-ui":{"2":1452},"@verdaccio/e2e-cli":{"2":1760},"@verdaccio/registry-cli":{"1":1637},"@verdaccio/yarn-plugin-npm-ping":{"0":133},"@verdaccio/yarn-plugin-npm-login":{"0":145},"@verdaccio/yarn-plugin-npm-deprecate":{"0":131},"@verdaccio/yarn-plugin-npm-unpublish":{"0":28},"@verdaccio/yarn-plugin-npm-star":{"0":16},"@verdaccio/yarn-import":{"0":31},"@verdaccio/utils":{"6":242251,"7":315422,"8":399728,"9":40},"verdaccio-audit":{"0":309,"1":1420,"8":1523,"9":5535,"10":51611,"11":7443,"12":18903,"13":638645,"14":418},"verdaccio-auth-memory":{"0":89,"1":7,"8":27,"9":1464,"10":46238,"11":38,"12":11,"13":5345,"14":162},"verdaccio-memory":{"0":8,"1":82,"2":6,"8":102,"9":64,"10":14739,"11":119,"12":55,"13":111,"14":206}}